{
    "name": "social-pressure",
    "schema": {
        "evidences": "evidences",
        "surface": "surface",
        "sankeys": "sankeys"
    },
    "mongodb": "mongodb://localhost/ivl",
    "campaign": "overwritewithenvorcommandline",

    "watch": [
        "bin/social-pressure.js",
        "campaigns/*/pugs/*.pug",
        "campaigns/*/*.js",
        "campaigns/*/*.css",
        "routes/*.js",
        "lib/*.js",
        "dist/*/**"
    ],
    "verbose": true,
    "exitcrash": false,
    "env": {
        "DEBUG": "*,-ffi:*,-ref*,-send,-express:*"
    },
    "ext": "js css json pug"
}
